timefarsi/__init__.py
timefarsi/events/__init__.py
timefarsi/events/events.py
timefarsi/times/__init__.py
timefarsi/times/times.py
timefarsi-0.0.1.dist-info/LICENSE
timefarsi-0.0.1.dist-info/METADATA
timefarsi-0.0.1.dist-info/WHEEL
timefarsi-0.0.1.dist-info/top_level.txt
timefarsi-0.0.1.dist-info/RECORD
