Metadata-Version: 2.2
Name: TimeFarsi
Version: 0.0.1
Summary: The Time...
Author-email: Mohammad Parsa Mortazavi <mohammadparsa9053@gmail.com>
Project-URL: Homepage, https://pypi.org/project/timefarsi
Classifier: Programming Language :: Python :: 3
Classifier: Operating System :: OS Independent
Classifier: License :: OSI Approved :: MIT License
Requires-Python: >=3.8
License-File: LICENSE
